[
  {
    "companyId1": 119,
    "companyId2": 0,
    "protocolId": 2,
    "networkId": 0,
    "flags": 49155,
    "mac": "32317a8d89f1",
    "recordType": 32,
    "recordNumber": 4775,
    "epoch": 1688682712,
    "data": "68e16341",
    "resetCount": 0,
    "rssi": "-35",
    "observedMac": "01F1898D7A3132",
    "productId": 1,
    "firmwareVersion": "2.0.3",
    "firmwareType": 0,
    "configVersion": 0,
    "bootLoaderVersion": "0.0.0",
    "hardwareVersion": 0,
    "nameLength": 14,
    "fullName": 9,
    "name": "Cold_Pressure",
    "thingTypeName": "BT610-Sensor",
    "decodedFlags": {
      "qrtcSet": true,
      "activeMode": true,
      "flagSet": false,
      "temperatureAlarm1State": false,
      "temperatureAlarm2State": false,
      "temperatureAlarm3State": false,
      "temperatureAlarm4State": false,
      "batteryLowAlarm": false,
      "analogAlarm1State": false,
      "analogAlarm2State": false,
      "analogAlarm3State": false,
      "analogAlarm4State": false,
      "digitalAlarm1State": false,
      "digitalAlarm2State": false,
      "tamperSwitchStatus": true,
      "magnetState": true
    },
    "record": {
      "key": "pressure2",
      "value": 14.242530822753906
    }
  },
  {
    "companyId1": 119,
    "companyId2": 0,
    "protocolId": 2,
    "networkId": 0,
    "flags": 49155,
    "mac": "e946207db7f9",
    "recordType": 32,
    "recordNumber": 4638,
    "epoch": 1688682665,
    "data": "68e16341",
    "resetCount": 0,
    "rssi": "-27",
    "observedMac": "01F9B77D2046E9",
    "productId": 1,
    "firmwareVersion": "2.0.3",
    "firmwareType": 0,
    "configVersion": 0,
    "bootLoaderVersion": "0.0.0",
    "hardwareVersion": 0,
    "nameLength": 13,
    "fullName": 9,
    "name": "Hot_Pressure",
    "thingTypeName": "BT610-Sensor",
    "decodedFlags": {
      "qrtcSet": true,
      "activeMode": true,
      "flagSet": false,
      "temperatureAlarm1State": false,
      "temperatureAlarm2State": false,
      "temperatureAlarm3State": false,
      "temperatureAlarm4State": false,
      "batteryLowAlarm": false,
      "analogAlarm1State": false,
      "analogAlarm2State": false,
      "analogAlarm3State": false,
      "analogAlarm4State": false,
      "digitalAlarm1State": false,
      "digitalAlarm2State": false,
      "tamperSwitchStatus": true,
      "magnetState": true
    },
    "record": {
      "key": "pressure2",
      "value": 14.242530822753906
    }
  },
  {
    "companyId1": 119,
    "companyId2": 0,
    "protocolId": 2,
    "networkId": 0,
    "flags": 49155,
    "mac": "e946207db7f9",
    "recordType": 32,
    "recordNumber": 4638,
    "epoch": 1688682665,
    "data": "68e16341",
    "resetCount": 0,
    "rssi": "-27",
    "observedMac": "01F9B77D2046E9",
    "productId": 1,
    "firmwareVersion": "2.0.3",
    "firmwareType": 0,
    "configVersion": 0,
    "bootLoaderVersion": "0.0.0",
    "hardwareVersion": 0,
    "nameLength": 13,
    "fullName": 9,
    "name": "Hot_Pressure",
    "thingTypeName": "BT610-Sensor",
    "decodedFlags": {
      "qrtcSet": true,
      "activeMode": true,
      "flagSet": false,
      "temperatureAlarm1State": false,
      "temperatureAlarm2State": false,
      "temperatureAlarm3State": false,
      "temperatureAlarm4State": false,
      "batteryLowAlarm": false,
      "analogAlarm1State": false,
      "analogAlarm2State": false,
      "analogAlarm3State": false,
      "analogAlarm4State": false,
      "digitalAlarm1State": false,
      "digitalAlarm2State": false,
      "tamperSwitchStatus": true,
      "magnetState": true
    },
    "record": {
      "key": "pressure2",
      "value": 14.242530822753906
    }
  },
  {
    "companyId1": 119,
    "companyId2": 0,
    "protocolId": 2,
    "networkId": 0,
    "flags": 49155,
    "mac": "860d68ea14c3",
    "recordType": 18,
    "recordNumber": 7779,
    "epoch": 1688682375,
    "data": "6016d741",
    "resetCount": 0,
    "rssi": "-29",
    "observedMac": "01C314EA680D86",
    "productId": 1,
    "firmwareVersion": "2.0.3",
    "firmwareType": 0,
    "configVersion": 0,
    "bootLoaderVersion": "0.0.0",
    "hardwareVersion": 0,
    "nameLength": 21,
    "fullName": 9,
    "name": "Hot_Cold_Temperature",
    "thingTypeName": "BT610-Sensor",
    "decodedFlags": {
      "qrtcSet": true,
      "activeMode": true,
      "flagSet": false,
      "temperatureAlarm1State": false,
      "temperatureAlarm2State": false,
      "temperatureAlarm3State": false,
      "temperatureAlarm4State": false,
      "batteryLowAlarm": false,
      "analogAlarm1State": false,
      "analogAlarm2State": false,
      "analogAlarm3State": false,
      "analogAlarm4State": false,
      "digitalAlarm1State": false,
      "digitalAlarm2State": false,
      "tamperSwitchStatus": true,
      "magnetState": true
    },
    "record": {
      "key": "temperatureResult1",
      "value": 26.88592529296875
    }
  },
  {
    "companyId1": 119,
    "companyId2": 0,
    "protocolId": 2,
    "networkId": 0,
    "flags": 49155,
    "mac": "860d68ea14c3",
    "recordType": 18,
    "recordNumber": 7779,
    "epoch": 1688682375,
    "data": "6016d741",
    "resetCount": 0,
    "rssi": "-30",
    "observedMac": "01C314EA680D86",
    "productId": 1,
    "firmwareVersion": "2.0.3",
    "firmwareType": 0,
    "configVersion": 0,
    "bootLoaderVersion": "0.0.0",
    "hardwareVersion": 0,
    "nameLength": 21,
    "fullName": 9,
    "name": "Hot_Cold_Temperature",
    "thingTypeName": "BT610-Sensor",
    "decodedFlags": {
      "qrtcSet": true,
      "activeMode": true,
      "flagSet": false,
      "temperatureAlarm1State": false,
      "temperatureAlarm2State": false,
      "temperatureAlarm3State": false,
      "temperatureAlarm4State": false,
      "batteryLowAlarm": false,
      "analogAlarm1State": false,
      "analogAlarm2State": false,
      "analogAlarm3State": false,
      "analogAlarm4State": false,
      "digitalAlarm1State": false,
      "digitalAlarm2State": false,
      "tamperSwitchStatus": true,
      "magnetState": true
    },
    "record": {
      "key": "temperatureResult1",
      "value": 26.88592529296875
    }
  },
  {
    "companyId1": 119,
    "companyId2": 0,
    "protocolId": 2,
    "networkId": 0,
    "flags": 49155,
    "mac": "e946207db7f9",
    "recordType": 32,
    "recordNumber": 4638,
    "epoch": 1688682665,
    "data": "68e16341",
    "resetCount": 0,
    "rssi": "-31",
    "observedMac": "01F9B77D2046E9",
    "productId": 1,
    "firmwareVersion": "2.0.3",
    "firmwareType": 0,
    "configVersion": 0,
    "bootLoaderVersion": "0.0.0",
    "hardwareVersion": 0,
    "nameLength": 13,
    "fullName": 9,
    "name": "Hot_Pressure",
    "thingTypeName": "BT610-Sensor",
    "decodedFlags": {
      "qrtcSet": true,
      "activeMode": true,
      "flagSet": false,
      "temperatureAlarm1State": false,
      "temperatureAlarm2State": false,
      "temperatureAlarm3State": false,
      "temperatureAlarm4State": false,
      "batteryLowAlarm": false,
      "analogAlarm1State": false,
      "analogAlarm2State": false,
      "analogAlarm3State": false,
      "analogAlarm4State": false,
      "digitalAlarm1State": false,
      "digitalAlarm2State": false,
      "tamperSwitchStatus": true,
      "magnetState": true
    },
    "record": {
      "key": "pressure2",
      "value": 14.242530822753906
    }
  },
  {
    "companyId1": 119,
    "companyId2": 0,
    "protocolId": 2,
    "networkId": 0,
    "flags": 49155,
    "mac": "32317a8d89f1",
    "recordType": 32,
    "recordNumber": 4781,
    "epoch": 1688682732,
    "data": "f49c5f41",
    "resetCount": 0,
    "rssi": "-41",
    "observedMac": "01F1898D7A3132",
    "productId": 1,
    "firmwareVersion": "2.0.3",
    "firmwareType": 0,
    "configVersion": 0,
    "bootLoaderVersion": "0.0.0",
    "hardwareVersion": 0,
    "nameLength": 14,
    "fullName": 9,
    "name": "Cold_Pressure",
    "thingTypeName": "BT610-Sensor",
    "decodedFlags": {
      "qrtcSet": true,
      "activeMode": true,
      "flagSet": false,
      "temperatureAlarm1State": false,
      "temperatureAlarm2State": false,
      "temperatureAlarm3State": false,
      "temperatureAlarm4State": false,
      "batteryLowAlarm": false,
      "analogAlarm1State": false,
      "analogAlarm2State": false,
      "analogAlarm3State": false,
      "analogAlarm4State": false,
      "digitalAlarm1State": false,
      "digitalAlarm2State": false,
      "tamperSwitchStatus": true,
      "magnetState": true
    },
    "record": {
      "key": "pressure2",
      "value": 13.975818634033203
    }
  },
  {
    "companyId1": 119,
    "companyId2": 0,
    "protocolId": 2,
    "networkId": 0,
    "flags": 49155,
    "mac": "860d68ea14c3",
    "recordType": 18,
    "recordNumber": 7779,
    "epoch": 1688682375,
    "data": "6016d741",
    "resetCount": 0,
    "rssi": "-30",
    "observedMac": "01C314EA680D86",
    "productId": 1,
    "firmwareVersion": "2.0.3",
    "firmwareType": 0,
    "configVersion": 0,
    "bootLoaderVersion": "0.0.0",
    "hardwareVersion": 0,
    "nameLength": 21,
    "fullName": 9,
    "name": "Hot_Cold_Temperature",
    "thingTypeName": "BT610-Sensor",
    "decodedFlags": {
      "qrtcSet": true,
      "activeMode": true,
      "flagSet": false,
      "temperatureAlarm1State": false,
      "temperatureAlarm2State": false,
      "temperatureAlarm3State": false,
      "temperatureAlarm4State": false,
      "batteryLowAlarm": false,
      "analogAlarm1State": false,
      "analogAlarm2State": false,
      "analogAlarm3State": false,
      "analogAlarm4State": false,
      "digitalAlarm1State": false,
      "digitalAlarm2State": false,
      "tamperSwitchStatus": true,
      "magnetState": true
    },
    "record": {
      "key": "temperatureResult1",
      "value": 26.88592529296875
    }
  },
  {
    "companyId1": 119,
    "companyId2": 0,
    "protocolId": 2,
    "networkId": 0,
    "flags": 49155,
    "mac": "32317a8d89f1",
    "recordType": 31,
    "recordNumber": 4783,
    "epoch": 1688682742,
    "data": "68e16341",
    "resetCount": 0,
    "rssi": "-41",
    "observedMac": "01F1898D7A3132",
    "productId": 1,
    "firmwareVersion": "2.0.3",
    "firmwareType": 0,
    "configVersion": 0,
    "bootLoaderVersion": "0.0.0",
    "hardwareVersion": 0,
    "nameLength": 14,
    "fullName": 9,
    "name": "Cold_Pressure",
    "thingTypeName": "BT610-Sensor",
    "decodedFlags": {
      "qrtcSet": true,
      "activeMode": true,
      "flagSet": false,
      "temperatureAlarm1State": false,
      "temperatureAlarm2State": false,
      "temperatureAlarm3State": false,
      "temperatureAlarm4State": false,
      "batteryLowAlarm": false,
      "analogAlarm1State": false,
      "analogAlarm2State": false,
      "analogAlarm3State": false,
      "analogAlarm4State": false,
      "digitalAlarm1State": false,
      "digitalAlarm2State": false,
      "tamperSwitchStatus": true,
      "magnetState": true
    },
    "record": {
      "key": "pressure1",
      "value": 14.242530822753906
    }
  },
  {
    "companyId1": 119,
    "companyId2": 0,
    "protocolId": 2,
    "networkId": 0,
    "flags": 49155,
    "mac": "860d68ea14c3",
    "recordType": 18,
    "recordNumber": 7779,
    "epoch": 1688682375,
    "data": "6016d741",
    "resetCount": 0,
    "rssi": "-29",
    "observedMac": "01C314EA680D86",
    "productId": 1,
    "firmwareVersion": "2.0.3",
    "firmwareType": 0,
    "configVersion": 0,
    "bootLoaderVersion": "0.0.0",
    "hardwareVersion": 0,
    "nameLength": 21,
    "fullName": 9,
    "name": "Hot_Cold_Temperature",
    "thingTypeName": "BT610-Sensor",
    "decodedFlags": {
      "qrtcSet": true,
      "activeMode": true,
      "flagSet": false,
      "temperatureAlarm1State": false,
      "temperatureAlarm2State": false,
      "temperatureAlarm3State": false,
      "temperatureAlarm4State": false,
      "batteryLowAlarm": false,
      "analogAlarm1State": false,
      "analogAlarm2State": false,
      "analogAlarm3State": false,
      "analogAlarm4State": false,
      "digitalAlarm1State": false,
      "digitalAlarm2State": false,
      "tamperSwitchStatus": true,
      "magnetState": true
    },
    "record": {
      "key": "temperatureResult1",
      "value": 26.88592529296875
    }
  },
  {
    "companyId1": 119,
    "companyId2": 0,
    "protocolId": 2,
    "networkId": 0,
    "flags": 49155,
    "mac": "e946207db7f9",
    "recordType": 32,
    "recordNumber": 4638,
    "epoch": 1688682665,
    "data": "68e16341",
    "resetCount": 0,
    "rssi": "-27",
    "observedMac": "01F9B77D2046E9",
    "productId": 1,
    "firmwareVersion": "2.0.3",
    "firmwareType": 0,
    "configVersion": 0,
    "bootLoaderVersion": "0.0.0",
    "hardwareVersion": 0,
    "nameLength": 13,
    "fullName": 9,
    "name": "Hot_Pressure",
    "thingTypeName": "BT610-Sensor",
    "decodedFlags": {
      "qrtcSet": true,
      "activeMode": true,
      "flagSet": false,
      "temperatureAlarm1State": false,
      "temperatureAlarm2State": false,
      "temperatureAlarm3State": false,
      "temperatureAlarm4State": false,
      "batteryLowAlarm": false,
      "analogAlarm1State": false,
      "analogAlarm2State": false,
      "analogAlarm3State": false,
      "analogAlarm4State": false,
      "digitalAlarm1State": false,
      "digitalAlarm2State": false,
      "tamperSwitchStatus": true,
      "magnetState": true
    },
    "record": {
      "key": "pressure2",
      "value": 14.242530822753906
    }
  },
  {
    "companyId1": 119,
    "companyId2": 0,
    "protocolId": 2,
    "networkId": 0,
    "flags": 49155,
    "mac": "e946207db7f9",
    "recordType": 32,
    "recordNumber": 4638,
    "epoch": 1688682665,
    "data": "68e16341",
    "resetCount": 0,
    "rssi": "-25",
    "observedMac": "01F9B77D2046E9",
    "productId": 1,
    "firmwareVersion": "2.0.3",
    "firmwareType": 0,
    "configVersion": 0,
    "bootLoaderVersion": "0.0.0",
    "hardwareVersion": 0,
    "nameLength": 13,
    "fullName": 9,
    "name": "Hot_Pressure",
    "thingTypeName": "BT610-Sensor",
    "decodedFlags": {
      "qrtcSet": true,
      "activeMode": true,
      "flagSet": false,
      "temperatureAlarm1State": false,
      "temperatureAlarm2State": false,
      "temperatureAlarm3State": false,
      "temperatureAlarm4State": false,
      "batteryLowAlarm": false,
      "analogAlarm1State": false,
      "analogAlarm2State": false,
      "analogAlarm3State": false,
      "analogAlarm4State": false,
      "digitalAlarm1State": false,
      "digitalAlarm2State": false,
      "tamperSwitchStatus": true,
      "magnetState": true
    },
    "record": {
      "key": "pressure2",
      "value": 14.242530822753906
    }
  },
  {
    "companyId1": 119,
    "companyId2": 0,
    "protocolId": 2,
    "networkId": 0,
    "flags": 49155,
    "mac": "860d68ea14c3",
    "recordType": 18,
    "recordNumber": 7783,
    "epoch": 1688682385,
    "data": "5045d741",
    "resetCount": 0,
    "rssi": "-29",
    "observedMac": "01C314EA680D86",
    "productId": 1,
    "firmwareVersion": "2.0.3",
    "firmwareType": 0,
    "configVersion": 0,
    "bootLoaderVersion": "0.0.0",
    "hardwareVersion": 0,
    "nameLength": 21,
    "fullName": 9,
    "name": "Hot_Cold_Temperature",
    "thingTypeName": "BT610-Sensor",
    "decodedFlags": {
      "qrtcSet": true,
      "activeMode": true,
      "flagSet": false,
      "temperatureAlarm1State": false,
      "temperatureAlarm2State": false,
      "temperatureAlarm3State": false,
      "temperatureAlarm4State": false,
      "batteryLowAlarm": false,
      "analogAlarm1State": false,
      "analogAlarm2State": false,
      "analogAlarm3State": false,
      "analogAlarm4State": false,
      "digitalAlarm1State": false,
      "digitalAlarm2State": false,
      "tamperSwitchStatus": true,
      "magnetState": true
    },
    "record": {
      "key": "temperatureResult1",
      "value": 26.908843994140625
    }
  },
  {
    "companyId1": 119,
    "companyId2": 0,
    "protocolId": 2,
    "networkId": 0,
    "flags": 49155,
    "mac": "860d68ea14c3",
    "recordType": 18,
    "recordNumber": 7783,
    "epoch": 1688682385,
    "data": "5045d741",
    "resetCount": 0,
    "rssi": "-29",
    "observedMac": "01C314EA680D86",
    "productId": 1,
    "firmwareVersion": "2.0.3",
    "firmwareType": 0,
    "configVersion": 0,
    "bootLoaderVersion": "0.0.0",
    "hardwareVersion": 0,
    "nameLength": 21,
    "fullName": 9,
    "name": "Hot_Cold_Temperature",
    "thingTypeName": "BT610-Sensor",
    "decodedFlags": {
      "qrtcSet": true,
      "activeMode": true,
      "flagSet": false,
      "temperatureAlarm1State": false,
      "temperatureAlarm2State": false,
      "temperatureAlarm3State": false,
      "temperatureAlarm4State": false,
      "batteryLowAlarm": false,
      "analogAlarm1State": false,
      "analogAlarm2State": false,
      "analogAlarm3State": false,
      "analogAlarm4State": false,
      "digitalAlarm1State": false,
      "digitalAlarm2State": false,
      "tamperSwitchStatus": true,
      "magnetState": true
    },
    "record": {
      "key": "temperatureResult1",
      "value": 26.908843994140625
    }
  },
  {
    "companyId1": 119,
    "companyId2": 0,
    "protocolId": 2,
    "networkId": 0,
    "flags": 49155,
    "mac": "e946207db7f9",
    "recordType": 32,
    "recordNumber": 4638,
    "epoch": 1688682665,
    "data": "68e16341",
    "resetCount": 0,
    "rssi": "-27",
    "observedMac": "01F9B77D2046E9",
    "productId": 1,
    "firmwareVersion": "2.0.3",
    "firmwareType": 0,
    "configVersion": 0,
    "bootLoaderVersion": "0.0.0",
    "hardwareVersion": 0,
    "nameLength": 13,
    "fullName": 9,
    "name": "Hot_Pressure",
    "thingTypeName": "BT610-Sensor",
    "decodedFlags": {
      "qrtcSet": true,
      "activeMode": true,
      "flagSet": false,
      "temperatureAlarm1State": false,
      "temperatureAlarm2State": false,
      "temperatureAlarm3State": false,
      "temperatureAlarm4State": false,
      "batteryLowAlarm": false,
      "analogAlarm1State": false,
      "analogAlarm2State": false,
      "analogAlarm3State": false,
      "analogAlarm4State": false,
      "digitalAlarm1State": false,
      "digitalAlarm2State": false,
      "tamperSwitchStatus": true,
      "magnetState": true
    },
    "record": {
      "key": "pressure2",
      "value": 14.242530822753906
    }
  },
  {
    "companyId1": 119,
    "companyId2": 0,
    "protocolId": 2,
    "networkId": 0,
    "flags": 49155,
    "mac": "e946207db7f9",
    "recordType": 32,
    "recordNumber": 4638,
    "epoch": 1688682665,
    "data": "68e16341",
    "resetCount": 0,
    "rssi": "-24",
    "observedMac": "01F9B77D2046E9",
    "productId": 1,
    "firmwareVersion": "2.0.3",
    "firmwareType": 0,
    "configVersion": 0,
    "bootLoaderVersion": "0.0.0",
    "hardwareVersion": 0,
    "nameLength": 13,
    "fullName": 9,
    "name": "Hot_Pressure",
    "thingTypeName": "BT610-Sensor",
    "decodedFlags": {
      "qrtcSet": true,
      "activeMode": true,
      "flagSet": false,
      "temperatureAlarm1State": false,
      "temperatureAlarm2State": false,
      "temperatureAlarm3State": false,
      "temperatureAlarm4State": false,
      "batteryLowAlarm": false,
      "analogAlarm1State": false,
      "analogAlarm2State": false,
      "analogAlarm3State": false,
      "analogAlarm4State": false,
      "digitalAlarm1State": false,
      "digitalAlarm2State": false,
      "tamperSwitchStatus": true,
      "magnetState": true
    },
    "record": {
      "key": "pressure2",
      "value": 14.242530822753906
    }
  },
  {
    "companyId1": 119,
    "companyId2": 0,
    "protocolId": 2,
    "networkId": 0,
    "flags": 49155,
    "mac": "32317a8d89f1",
    "recordType": 32,
    "recordNumber": 4787,
    "epoch": 1688682753,
    "data": "68e16341",
    "resetCount": 0,
    "rssi": "-37",
    "observedMac": "01F1898D7A3132",
    "productId": 1,
    "firmwareVersion": "2.0.3",
    "firmwareType": 0,
    "configVersion": 0,
    "bootLoaderVersion": "0.0.0",
    "hardwareVersion": 0,
    "nameLength": 14,
    "fullName": 9,
    "name": "Cold_Pressure",
    "thingTypeName": "BT610-Sensor",
    "decodedFlags": {
      "qrtcSet": true,
      "activeMode": true,
      "flagSet": false,
      "temperatureAlarm1State": false,
      "temperatureAlarm2State": false,
      "temperatureAlarm3State": false,
      "temperatureAlarm4State": false,
      "batteryLowAlarm": false,
      "analogAlarm1State": false,
      "analogAlarm2State": false,
      "analogAlarm3State": false,
      "analogAlarm4State": false,
      "digitalAlarm1State": false,
      "digitalAlarm2State": false,
      "tamperSwitchStatus": true,
      "magnetState": true
    },
    "record": {
      "key": "pressure2",
      "value": 14.242530822753906
    }
  },
  {
    "companyId1": 119,
    "companyId2": 0,
    "protocolId": 2,
    "networkId": 0,
    "flags": 49155,
    "mac": "32317a8d89f1",
    "recordType": 31,
    "recordNumber": 4789,
    "epoch": 1688682763,
    "data": "dc256841",
    "resetCount": 0,
    "rssi": "-35",
    "observedMac": "01F1898D7A3132",
    "productId": 1,
    "firmwareVersion": "2.0.3",
    "firmwareType": 0,
    "configVersion": 0,
    "bootLoaderVersion": "0.0.0",
    "hardwareVersion": 0,
    "nameLength": 14,
    "fullName": 9,
    "name": "Cold_Pressure",
    "thingTypeName": "BT610-Sensor",
    "decodedFlags": {
      "qrtcSet": true,
      "activeMode": true,
      "flagSet": false,
      "temperatureAlarm1State": false,
      "temperatureAlarm2State": false,
      "temperatureAlarm3State": false,
      "temperatureAlarm4State": false,
      "batteryLowAlarm": false,
      "analogAlarm1State": false,
      "analogAlarm2State": false,
      "analogAlarm3State": false,
      "analogAlarm4State": false,
      "digitalAlarm1State": false,
      "digitalAlarm2State": false,
      "tamperSwitchStatus": true,
      "magnetState": true
    },
    "record": {
      "key": "pressure1",
      "value": 14.50924301147461
    }
  }
]